{
  "sections": {
    "main": {
      "type": "contactPage",
      "settings": {
      }
    },
    "7b2a3596-af09-43c7-9fbf-0edc33b9bdfb": {
      "type": "subtitle-title",
      "settings": {
        "anchor": "",
        "marTop": "50",
        "marBottom": "0",
        "marTopMob": "50",
        "marBottomMob": "0",
        "padTop": "150",
        "padBottom": "0",
        "padLeft": "50",
        "padRight": "50",
        "padTopMob": "20",
        "padBottomMob": "20",
        "padLeftMob": "10",
        "padRightMob": "10",
        "backgroundColor": "#f5f1eb",
        "subtext": "Start your Weldwork journey.",
        "reverse_subtitle": true,
        "subtextSize": "48",
        "subtextWeight": "400",
        "subtextLine": "48",
        "subtextLetter": "",
        "subtextColor": "#1f2021",
        "subtextAlign": "center",
        "subtextMarBottom": "24",
        "subtextSizeMob": "36",
        "subtextLineMob": "40",
        "subtextLetterMob": "",
        "subtextColorMob": "",
        "subtextAlignMob": "center",
        "subtextMarBottomMob": "20",
        "title": "Our door is always open.",
        "titleSize": "32",
        "titleLine": "36",
        "titleLetter": "",
        "titleColor": "",
        "titleAlign": "center",
        "titleMarBottom": "",
        "titleSizeMob": "18",
        "titleLineMob": "20",
        "titleLetterMob": "",
        "titleColorMob": "#1f2021",
        "titleAlignMob": "center",
        "titleMarBottomMob": ""
      }
    },
    "7b2a3596-af09-43c7-9fbf-0edc33b9asdfa": {
      "type": "subtitle-title",
      "settings": {
        "anchor": "",
        "marTop": "0",
        "marBottom": "0",
        "marTopMob": "0",
        "marBottomMob": "0",
        "padTop": "25",
        "padBottom": "50",
        "padLeft": "250",
        "padRight": "250",
        "padTopMob": "20",
        "padBottomMob": "20",
        "padLeftMob": "10",
        "padRightMob": "10",
        "backgroundColor": "#f5f1eb",
        "subtext": "",
        "reverse_subtitle": false,
        "subtextSize": "48",
        "subtextWeight": "400",
        "subtextLine": "48",
        "subtextLetter": "",
        "subtextColor": "#1f2021",
        "subtextAlign": "center",
        "subtextMarBottom": "24",
        "subtextSizeMob": "36",
        "subtextLineMob": "40",
        "subtextLetterMob": "",
        "subtextColorMob": "",
        "subtextAlignMob": "center",
        "subtextMarBottomMob": "20",
        "title": "When you’re ready to start please complete the contact form. One of our sales specialists will follow up with you to discuss your project.",
        "titleSize": "24",
        "titleLine": "28",
        "titleLetter": "",
        "titleColor": "",
        "titleAlign": "center",
        "titleMarBottom": "",
        "titleSizeMob": "18",
        "titleLineMob": "24",
        "titleLetterMob": "",
        "titleColorMob": "#1f2021",
        "titleAlignMob": "center",
        "titleMarBottomMob": ""
      }
    },
    "1bf8d524-35c7-4dc8-8fb9-2f5d4a0cb35f": {
      "type": "advanced-content",
      "blocks": {
        "template--15807312003268__1bf8d524-35c7-4dc8-8fb9-2f5d4a0cb35f-167293931170f4af77-0": {
          "type": "html",
          "settings": {
            "code": "<!--pifyform-start--><iframe allowtransparency=\"true\" scrolling=\"no\" style=\"display: block; min-width: 100%; width: 100px; border: none; overflow: auto;\" src=\"https:\/\/form-builder-an.pifyapp.com\/form\/s\/6404\" height=\"1600\" frameborder=\"0\"><\/iframe> <!--pifyform-end-->\n\n<style>\n.shopify-section {\n  background-color: #F5F1EB;\n}\n.linecustom {\n  background-color: #fff;\n}\n<\/style>",
            "width": "100%",
            "alignment": "top-middle"
          }
        }
      },
      "block_order": [
        "template--15807312003268__1bf8d524-35c7-4dc8-8fb9-2f5d4a0cb35f-167293931170f4af77-0"
      ],
      "settings": {
      }
    },
    "1637759478272e02f7": {
      "type": "aboutMainSection",
      "disabled": true,
      "settings": {
        "dark": true,
        "marTop": "0",
        "marBottom": "0",
        "marTopMob": "",
        "marBottomMob": "",
        "padTop": "173",
        "padBottom": "100",
        "padLeft": "300",
        "padRight": "300",
        "padTopMob": "144",
        "padBottomMob": "0",
        "padLeftMob": "20",
        "padRightMob": "20",
        "backgroundColor": "#000000",
        "subtext": "NEED TO CONTACT US?",
        "subtextSize": "16",
        "subtextLine": "20.8",
        "subtextLetter": "4",
        "subtextColor": "#c3c3c3",
        "subtextAlign": "center",
        "subtextMarBottom": "24",
        "subtextSizeMob": "12",
        "subtextLineMob": "21.6",
        "subtextLetterMob": "",
        "subtextColorMob": "",
        "subtextAlignMob": "center",
        "subtextMarBottomMob": "16",
        "title": "We're always there",
        "titleSize": "120",
        "titleLine": "108",
        "titleLetter": "-3",
        "titleColor": "#ffffff",
        "titleAlign": "center",
        "titleMarBottom": "",
        "titleSizeMob": "60",
        "titleLineMob": "54",
        "titleLetterMob": "",
        "titleColorMob": "",
        "titleAlignMob": "center",
        "titleMarBottomMob": "",
        "buttonText": "",
        "buttonLink": ""
      }
    },
    "16377595427c9c2aa9": {
      "type": "emptyDiv",
      "disabled": true,
      "settings": {
        "height": "33"
      }
    },
    "d23d71fe-07ec-4950-857b-038f1be9c822": {
      "type": "titleText",
      "disabled": true,
      "settings": {
        "titleWidth": "42.37",
        "titleMargin": "8.92",
        "marTop": "120",
        "marBottom": "20",
        "marTopMob": "",
        "marBottomMob": "",
        "padTop": "20",
        "padBottom": "20",
        "padLeft": "",
        "padRight": "",
        "padTopMob": "",
        "padBottomMob": "",
        "padLeftMob": "",
        "padRightMob": "",
        "backgroundColor": "",
        "title": "Lorem Ipsum",
        "titleSize": "16",
        "titleWeight": "400",
        "titleLine": "",
        "titleLetter": "",
        "titleColor": "#1f2021",
        "titleAlign": "center",
        "titleMarBottom": "",
        "titleSizeMob": "",
        "titleLineMob": "",
        "titleLetterMob": "",
        "titleColorMob": "",
        "titleAlignMob": "center",
        "titleMarBottomMob": "",
        "subtext": "Subtitle",
        "subtextSize": "14",
        "subtextWeight": "400",
        "subtextLine": "0",
        "subtextLetter": "",
        "subtextColor": "#1f2021",
        "subtextAlign": "center",
        "subtextMarBottom": "",
        "subtextSizeMob": "",
        "subtextLineMob": "",
        "subtextLetterMob": "",
        "subtextColorMob": "#1f2021",
        "subtextAlignMob": "center",
        "subtextMarBottomMob": ""
      }
    },
    "a9fdabcc-ea6e-4c6f-8635-5f68db1c7298": {
      "type": "Homepage_main_section",
      "disabled": true,
      "settings": {
        "dark": false,
        "sectionHeight": "80",
        "sectionHeightMobile": "75",
        "marTop": "",
        "marBottom": "",
        "marTopMob": "=",
        "marBottomMob": "",
        "padTop": "182",
        "padBottom": "",
        "padLeft": "144",
        "padRight": "",
        "padTopMob": "196",
        "padBottomMob": "",
        "padLeftMob": "20",
        "padRightMob": "20",
        "title": "Lorem ipsum dolor",
        "titleSize": "64",
        "titleLine": "99",
        "titleLetter": "-0.04",
        "titleColor": "#1f2021",
        "titleAlign": "left",
        "titleMarBottom": "35",
        "titleSizeMob": "40",
        "titleLineMob": "105",
        "titleLetterMob": "-0.03",
        "titleColorMob": "#ffffff",
        "titleAlignMob": "left",
        "titleMarBottomMob": "20",
        "subtext": "Lorem ipsum dolor sit amet.",
        "subtextSize": "20",
        "subtextLine": "150",
        "subtextLetter": "0",
        "subtextColor": "#ffffff",
        "subtextAlign": "left",
        "subtextMarBottom": "35",
        "subtextSizeMob": "16",
        "subtextLineMob": "150",
        "subtextLetterMob": "",
        "subtextColorMob": "#ffffff",
        "subtextAlignMob": "left",
        "subtextMarBottomMob": "32",
        "buttonText": "",
        "buttonLink": "",
        "buttonText2": "",
        "buttonLink2": ""
      }
    },
    "163845793952ec85ca": {
      "type": "contactSection",
      "disabled": true,
      "settings": {
        "marTop": "",
        "button-one": "Homeowner",
        "button_link-one": "shopify:\/\/pages\/residential",
        "button-two": "Builder",
        "button_link-two": "shopify:\/\/pages\/builder",
        "button-three": "Designer",
        "button_link-three": "shopify:\/\/pages\/designer",
        "button-four": "Architect",
        "button_link-four": "shopify:\/\/pages\/architect",
        "marBottom": "",
        "marTopMob": "",
        "marBottomMob": "",
        "padTop": "",
        "padBottom": "",
        "padLeft": "89",
        "padRight": "89",
        "padTopMob": "",
        "padBottomMob": "",
        "padLeftMob": "20",
        "padRightMob": "20",
        "backgroundColor": "rgba(0,0,0,0)",
        "boxBackgroundColor": "#f4f0ea",
        "title": "We’re just a message away",
        "titleSize": "56",
        "titleLine": "58.8",
        "titleLetter": "-2",
        "titleColor": "#000000",
        "titleAlign": "left",
        "titleMarBottom": "",
        "titleSizeMob": "36",
        "titleLineMob": "37.8",
        "titleLetterMob": "",
        "titleColorMob": "",
        "titleAlignMob": "center",
        "titleMarBottomMob": "44",
        "image": "shopify:\/\/shop_images\/Sam_Fingeroot.png",
        "textWidth": "37.54",
        "textMargin": "7.98",
        "textWidthMob": "43",
        "textMarginMob": "",
        "subtext": "Samantha Fingeroot",
        "subtextSize": "24",
        "subtextLine": "28.8",
        "subtextLetter": "",
        "subtextColor": "",
        "subtextAlign": "left",
        "subtextMarBottom": "17",
        "subtextSizeMob": "24",
        "subtextLineMob": "28.8",
        "subtextLetterMob": "",
        "subtextColorMob": "",
        "subtextAlignMob": "center",
        "subtextMarBottomMob": "16",
        "text": "Hey It's Samantha, you will be receiving an email within 24 hours to set up a call with one of our sales specialists!  We look forward to speaking with you about your upcoming interior steel door project.",
        "textSize": "16",
        "textLine": "24",
        "textLetter": "",
        "textColor": "#5e5e5e",
        "textAlign": "left",
        "textMarBottom": "",
        "textSizeMob": "16",
        "textLineMob": "24",
        "textLetterMob": "",
        "textColorMob": "",
        "textAlignMob": "center",
        "textMarBottomMob": "58"
      }
    },
    "163870694799c4cea8": {
      "type": "newMap",
      "disabled": true,
      "settings": {
        "marTop": "0",
        "marBottom": "0",
        "marTopMob": "",
        "marBottomMob": "",
        "padTop": "196",
        "padBottom": "10",
        "padLeft": "185",
        "padRight": "185",
        "padTopMob": "416",
        "padBottomMob": "80",
        "padLeftMob": "20",
        "padRightMob": "20",
        "backgroundImage": "shopify:\/\/shop_images\/5_1_84b9ec3e-93ea-4eef-92de-fa4b80777f39.jpg",
        "backgroundImageMob": "shopify:\/\/shop_images\/5_1.jpg",
        "textWidth": "51.86",
        "textMargin": "0",
        "textWidthMob": "100",
        "textMarginMob": "0",
        "title": "",
        "titleSize": "",
        "titleLine": "",
        "titleLetter": "",
        "titleColor": "",
        "titleAlign": "center",
        "titleMarBottom": "",
        "titleSizeMob": "",
        "titleLineMob": "",
        "titleLetterMob": "",
        "titleColorMob": "",
        "titleAlignMob": "center",
        "titleMarBottomMob": "",
        "iconWidth": "",
        "iconWidthMob": "",
        "backgroundColor": "#232323",
        "boxPadTop": "60",
        "boxPadBottom": "65",
        "boxPadLeft": "65",
        "boxPadRight": "65",
        "boxPadTopMob": "60",
        "boxPadBottomMob": "61",
        "boxPadLeftMob": "24",
        "boxPadRightMob": "24",
        "boxIconWidth": "",
        "boxIconWidthMob": "",
        "boxLink": "",
        "boxLinkText": "",
        "boxTitle": "Weldwork LLC",
        "boxTitleSize": "56",
        "boxTitleLine": "58.8",
        "boxTitleLetter": "-2",
        "boxTitleColor": "#ffffff",
        "boxTitleAlign": "left",
        "boxTitleMarBottom": "28",
        "boxTitleSizeMob": "36",
        "boxTitleLineMob": "37.8",
        "boxTitleLetterMob": "",
        "boxTitleColorMob": "",
        "boxTitleAlignMob": "left",
        "boxTitleMarBottomMob": "34",
        "subtext": "sales@weldwork.com<br>\n<a id=\"dial-phone\" href=\"tel:+1%20248-955-9990\">+1 248-955-9990<\/a>",
        "subtextSize": "26",
        "subtextLine": "40.8",
        "subtextLetter": "",
        "subtextColor": "#ffffff",
        "subtextAlign": "left",
        "subtextMarBottom": "68",
        "subtextSizeMob": "24",
        "subtextLineMob": "28.8",
        "subtextLetterMob": "",
        "subtextColorMob": "",
        "subtextAlignMob": "left",
        "subtextMarBottomMob": "136",
        "boxText": "4421 Delemere Blvd,<br> Royal Oak, MI 48073, <br>\nUnited States",
        "boxTextSize": "16",
        "boxTextLine": "24",
        "boxTextLetter": "",
        "boxTextColor": "#ffffff",
        "boxTextAlign": "left",
        "boxTextMarBottom": "",
        "boxTextSizeMob": "16",
        "boxTextLineMob": "24",
        "boxTextLetterMob": "",
        "boxTextColorMob": "",
        "boxTextAlignMob": "left",
        "boxTextMarBottomMob": ""
      }
    },
    "1638707941bbbe04d1": {
      "type": "imageBlockText",
      "disabled": true,
      "blocks": {
        "7ea65b1a-0799-45cc-a8e9-162f93e7682d": {
          "type": "Block",
          "settings": {
            "subtext": "The premier name in luxury interior steel doors",
            "weight": "400",
            "subtextSize": "56",
            "subtextLine": "58.8",
            "subtextLetter": "-2",
            "subtextColor": "#ffffff",
            "subtextAlign": "left",
            "subtextMarBottom": "32",
            "subtextSizeMob": "36",
            "subtextLineMob": "37.8",
            "subtextLetterMob": "",
            "subtextColorMob": "",
            "subtextAlignMob": "left",
            "subtextMarBottomMob": "32"
          }
        },
        "30b8f452-2675-4b3a-936f-b2dce0be103c": {
          "type": "Block",
          "settings": {
            "subtext": "Weldwork is home to the nation’s finest luxury steel doors, completely hand-crafted in the USA.",
            "weight": "300",
            "subtextSize": "16",
            "subtextLine": "24",
            "subtextLetter": "",
            "subtextColor": "#c3c3c3",
            "subtextAlign": "left",
            "subtextMarBottom": "32",
            "subtextSizeMob": "16",
            "subtextLineMob": "24",
            "subtextLetterMob": "",
            "subtextColorMob": "#c3c3c3",
            "subtextAlignMob": "left",
            "subtextMarBottomMob": "32"
          }
        }
      },
      "block_order": [
        "7ea65b1a-0799-45cc-a8e9-162f93e7682d",
        "30b8f452-2675-4b3a-936f-b2dce0be103c"
      ],
      "settings": {
        "marTop": "",
        "marBottom": "",
        "marTopMob": "",
        "marBottomMob": "",
        "padTop": "170",
        "padBottom": "0",
        "padLeft": "185",
        "padRight": "185",
        "padTopMob": "80",
        "padBottomMob": "72",
        "padLeftMob": "20",
        "padRightMob": "20",
        "backgroundColor": "#000000",
        "image": "shopify:\/\/shop_images\/210805-MV-LaMarreDavis_201-1_e88df338-d4bf-4f4f-8984-7412aff191d5.jpg",
        "textWidth": "41.49",
        "textMargin": "10.37",
        "textWidthMob": "100",
        "textMarginMob": "0",
        "link": "shopify:\/\/pages\/doors",
        "linkText": "Discover more"
      }
    },
    "1638708650494360e6": {
      "type": "border",
      "disabled": true,
      "settings": {
        "height": "56",
        "marTop": "0",
        "marBottom": "",
        "marTopMob": "",
        "marBottomMob": "",
        "padTop": "56",
        "padBottom": "",
        "padTopMob": "",
        "padBottomMob": "",
        "backgroundColor": "#000000",
        "borderSize": "1",
        "borderColor": "#c3c3c3",
        "zIndex": "3"
      }
    }
  },
  "order": [
    "main",
    "7b2a3596-af09-43c7-9fbf-0edc33b9bdfb",
    "7b2a3596-af09-43c7-9fbf-0edc33b9asdfa",
    "1bf8d524-35c7-4dc8-8fb9-2f5d4a0cb35f",
    "1637759478272e02f7",
    "16377595427c9c2aa9",
    "d23d71fe-07ec-4950-857b-038f1be9c822",
    "a9fdabcc-ea6e-4c6f-8635-5f68db1c7298",
    "163845793952ec85ca",
    "163870694799c4cea8",
    "1638707941bbbe04d1",
    "1638708650494360e6"
  ]
}